{"buckets": [0, 100, 147, 216, 317, 465, 682, 1001, 1469, 2156, 3164, 4644, 6816, 10004, 14683, 21550, 31629, 46422, 68134, 100000], "data": [{"date": "20180507", "count": 293, "sum": 1492148, "histogram": [0, 0, 1, 3, 4, 10, 3, 27, 28, 22, 36, 58, 89, 12, 0, 0, 0, 0, 0, 0], "label": ""}, {"date": "20180506", "count": 526, "sum": 2715412, "histogram": [2, 4, 7, 3, 5, 15, 6, 26, 44, 61, 88, 93, 151, 17, 2, 2, 0, 0, 0, 0], "label": ""}, {"date": "20180505", "count": 539, "sum": 2150289035, "histogram": [2, 4, 4, 4, 7, 7, 11, 19, 46, 57, 86, 119, 154, 17, 1, 0, 0, 0, 0, 1], "label": ""}, {"date": "20180504", "count": 633, "sum": 3291386, "histogram": [4, 5, 6, 11, 5, 11, 12, 36, 42, 68, 87, 157, 166, 19, 2, 1, 1, 0, 0, 0], "label": ""}, {"date": "20180503", "count": 685, "sum": 3154074, "histogram": [4, 6, 11, 11, 15, 14, 37, 41, 54, 72, 100, 140, 158, 22, 0, 0, 0, 0, 0, 0], "label": ""}, {"date": "20180502", "count": 659, "sum": 3320765, "histogram": [4, 3, 6, 11, 8, 14, 21, 25, 49, 66, 112, 145, 166, 28, 0, 1, 0, 0, 0, 0], "label": ""}, {"date": "20180501", "count": 629, "sum": 3334641, "histogram": [6, 4, 5, 6, 7, 9, 14, 30, 46, 76, 78, 125, 193, 29, 1, 0, 0, 0, 0, 0], "label": ""}, {"date": "20180430", "count": 625, "sum": 3214760, "histogram": [1, 5, 4, 8, 6, 13, 22, 30, 46, 68, 98, 126, 170, 26, 1, 0, 1, 0, 0, 0], "label": ""}, {"date": "20180429", "count": 663, "sum": 3177253, "histogram": [7, 8, 1, 6, 7, 12, 22, 25, 61, 98, 100, 124, 173, 18, 0, 1, 0, 0, 0, 0], "label": ""}, {"date": "20180428", "count": 553, "sum": 2918895, "histogram": [1, 4, 1, 7, 3, 12, 14, 24, 34, 67, 90, 101, 170, 24, 1, 0, 0, 0, 0, 0], "label": ""}, {"date": "20180427", "count": 630, "sum": 3169084, "histogram": [4, 5, 6, 4, 5, 22, 24, 28, 41, 71, 88, 142, 170, 18, 2, 0, 0, 0, 0, 0], "label": ""}, {"date": "20180426", "count": 723, "sum": 3676153, "histogram": [3, 4, 6, 10, 13, 11, 23, 31, 55, 82, 115, 141, 200, 27, 0, 2, 0, 0, 0, 0], "label": ""}, {"date": "20180425", "count": 740, "sum": 3873555, "histogram": [2, 4, 12, 18, 14, 10, 19, 26, 54, 72, 107, 168, 203, 27, 2, 1, 0, 1, 0, 0], "label": ""}, {"date": "20180424", "count": 819, "sum": 4302659, "histogram": [4, 4, 9, 3, 7, 24, 24, 30, 63, 100, 106, 164, 239, 40, 1, 1, 0, 0, 0, 0], "label": ""}, {"date": "20180423", "count": 620, "sum": 3146570, "histogram": [3, 2, 6, 4, 6, 8, 11, 37, 70, 61, 107, 115, 160, 28, 0, 1, 0, 1, 0, 0], "label": ""}, {"date": "20180422", "count": 653, "sum": 3284354, "histogram": [2, 6, 5, 5, 11, 9, 22, 39, 52, 82, 89, 121, 182, 25, 2, 1, 0, 0, 0, 0], "label": ""}, {"date": "20180421", "count": 561, "sum": 2598679, "histogram": [3, 13, 4, 10, 10, 18, 15, 30, 60, 68, 86, 77, 145, 19, 1, 2, 0, 0, 0, 0], "label": ""}, {"date": "20180420", "count": 693, "sum": 3484877, "histogram": [4, 6, 6, 6, 5, 9, 21, 40, 60, 67, 106, 148, 197, 16, 1, 1, 0, 0, 0, 0], "label": ""}, {"date": "20180419", "count": 610, "sum": 3039393, "histogram": [2, 5, 5, 6, 8, 8, 18, 25, 63, 57, 104, 128, 162, 18, 1, 0, 0, 0, 0, 0], "label": ""}, {"date": "20180418", "count": 586, "sum": 3012274, "histogram": [4, 3, 3, 8, 8, 13, 14, 33, 35, 68, 88, 121, 159, 27, 2, 0, 0, 0, 0, 0], "label": ""}, {"date": "20180417", "count": 659, "sum": 3511203, "histogram": [3, 4, 5, 4, 9, 15, 10, 22, 40, 84, 105, 128, 204, 24, 1, 1, 0, 0, 0, 0], "label": ""}, {"date": "20180416", "count": 393, "sum": 1882779, "histogram": [8, 3, 4, 3, 6, 10, 9, 16, 33, 47, 62, 80, 100, 11, 1, 0, 0, 0, 0, 0], "label": ""}, {"date": "20180415", "count": 1272, "sum": 6295091, "histogram": [9, 7, 8, 14, 22, 18, 36, 57, 108, 160, 221, 228, 337, 41, 6, 0, 0, 0, 0, 0], "label": ""}, {"date": "20180414", "count": 328, "sum": 1562089, "histogram": [6, 1, 3, 0, 3, 4, 16, 10, 29, 52, 48, 69, 77, 9, 1, 0, 0, 0, 0, 0], "label": ""}, {"date": "20180413", "count": 606, "sum": 3075309, "histogram": [5, 1, 5, 5, 8, 9, 18, 22, 48, 52, 111, 147, 160, 15, 0, 0, 0, 0, 0, 0], "label": ""}, {"date": "20180412", "count": 999, "sum": 5166167, "histogram": [7, 2, 3, 9, 8, 18, 25, 50, 77, 101, 172, 209, 283, 33, 2, 0, 0, 0, 0, 0], "label": ""}, {"date": "20180411", "count": 440, "sum": 2262876, "histogram": [1, 1, 3, 6, 8, 7, 10, 22, 46, 40, 62, 92, 123, 17, 2, 0, 0, 0, 0, 0], "label": ""}, {"date": "20180410", "count": 669, "sum": 3464495, "histogram": [5, 6, 7, 5, 10, 9, 17, 33, 42, 83, 97, 129, 199, 25, 1, 1, 0, 0, 0, 0], "label": ""}, {"date": "20180409", "count": 696, "sum": 3487102, "histogram": [1, 5, 7, 9, 10, 10, 24, 41, 56, 69, 113, 129, 195, 24, 3, 0, 0, 0, 0, 0], "label": ""}, {"date": "20180408", "count": 564, "sum": 2895338, "histogram": [8, 3, 1, 6, 3, 10, 19, 25, 50, 50, 89, 113, 162, 24, 1, 0, 0, 0, 0, 0], "label": ""}, {"date": "20180407", "count": 558, "sum": 2817954, "histogram": [2, 2, 3, 5, 8, 14, 16, 23, 47, 55, 92, 120, 149, 19, 3, 0, 0, 0, 0, 0], "label": ""}, {"date": "20180406", "count": 601, "sum": 2952317, "histogram": [6, 1, 3, 5, 11, 9, 18, 30, 49, 84, 85, 119, 168, 11, 2, 0, 0, 0, 0, 0], "label": ""}, {"date": "20180405", "count": 620, "sum": 3157001, "histogram": [4, 3, 7, 10, 13, 8, 17, 29, 51, 67, 91, 130, 157, 26, 5, 2, 0, 0, 0, 0], "label": ""}, {"date": "20180404", "count": 660, "sum": 3405221, "histogram": [4, 4, 4, 8, 15, 19, 18, 29, 41, 84, 92, 123, 194, 21, 2, 1, 1, 0, 0, 0], "label": ""}, {"date": "20180403", "count": 656, "sum": 3132585, "histogram": [2, 10, 9, 11, 11, 7, 22, 40, 59, 74, 94, 117, 173, 26, 1, 0, 0, 0, 0, 0], "label": ""}, {"date": "20180402", "count": 634, "sum": 3262398, "histogram": [0, 8, 6, 4, 8, 10, 22, 29, 52, 65, 97, 128, 178, 23, 4, 0, 0, 0, 0, 0], "label": ""}, {"date": "20180401", "count": 650, "sum": 3200471, "histogram": [1, 8, 2, 14, 6, 18, 19, 31, 48, 74, 100, 144, 163, 20, 1, 1, 0, 0, 0, 0], "label": ""}, {"date": "20180331", "count": 1216, "sum": 6444534, "histogram": [7, 3, 10, 18, 15, 27, 20, 50, 89, 131, 200, 247, 317, 79, 1, 0, 2, 0, 0, 0], "label": ""}, {"date": "20180330", "count": 453, "sum": 2424848, "histogram": [1, 4, 2, 13, 9, 7, 14, 17, 34, 40, 65, 80, 146, 18, 3, 0, 0, 0, 0, 0], "label": ""}, {"date": "20180329", "count": 626, "sum": 3039889, "histogram": [1, 5, 6, 4, 17, 15, 22, 23, 62, 75, 88, 120, 169, 18, 1, 0, 0, 0, 0, 0], "label": ""}, {"date": "20180328", "count": 716, "sum": 2162022869, "histogram": [2, 8, 6, 7, 8, 7, 20, 38, 61, 79, 115, 141, 178, 38, 5, 0, 1, 0, 0, 2], "label": ""}, {"date": "20180327", "count": 567, "sum": 2777124, "histogram": [8, 4, 5, 7, 7, 10, 22, 28, 33, 74, 78, 124, 147, 19, 1, 0, 0, 0, 0, 0], "label": ""}, {"date": "20180326", "count": 633, "sum": 3455508, "histogram": [1, 1, 2, 7, 4, 8, 24, 25, 50, 55, 90, 135, 203, 26, 2, 0, 0, 0, 0, 0], "label": ""}, {"date": "20180325", "count": 749, "sum": 4298605361, "histogram": [4, 7, 9, 5, 7, 12, 24, 34, 58, 97, 118, 167, 179, 23, 2, 1, 0, 0, 0, 2], "label": ""}, {"date": "20180324", "count": 589, "sum": 2992398, "histogram": [2, 4, 10, 4, 8, 9, 13, 27, 46, 65, 98, 115, 164, 22, 2, 0, 0, 0, 0, 0], "label": ""}, {"date": "20180323", "count": 556, "sum": 2768798, "histogram": [0, 2, 2, 8, 11, 11, 13, 16, 46, 64, 90, 131, 144, 18, 0, 0, 0, 0, 0, 0], "label": ""}, {"date": "20180322", "count": 800, "sum": 3985557, "histogram": [3, 3, 8, 6, 11, 15, 22, 32, 80, 93, 126, 150, 223, 26, 2, 0, 0, 0, 0, 0], "label": ""}, {"date": "20180321", "count": 852, "sum": 4361485, "histogram": [4, 5, 12, 8, 12, 13, 21, 52, 63, 92, 123, 171, 227, 44, 5, 0, 0, 0, 0, 0], "label": ""}, {"date": "20180320", "count": 503, "sum": 2520847, "histogram": [1, 3, 3, 5, 9, 10, 18, 19, 39, 57, 84, 105, 127, 23, 0, 0, 0, 0, 0, 0], "label": ""}, {"date": "20180319", "count": 671, "sum": 3438161, "histogram": [0, 6, 7, 2, 11, 13, 22, 24, 58, 89, 84, 151, 181, 21, 1, 0, 0, 0, 1, 0], "label": ""}, {"date": "20180318", "count": 652, "sum": 3320891, "histogram": [7, 4, 4, 5, 10, 10, 24, 39, 50, 64, 90, 134, 180, 27, 3, 1, 0, 0, 0, 0], "label": ""}, {"date": "20180317", "count": 639, "sum": 3291063, "histogram": [1, 2, 3, 4, 6, 14, 21, 34, 41, 74, 94, 149, 169, 23, 4, 0, 0, 0, 0, 0], "label": ""}, {"date": "20180316", "count": 662, "sum": 3354595, "histogram": [8, 2, 8, 4, 7, 10, 20, 23, 51, 76, 103, 139, 188, 22, 1, 0, 0, 0, 0, 0], "label": ""}, {"date": "20180315", "count": 636, "sum": 3270577, "histogram": [7, 7, 7, 6, 9, 23, 23, 19, 42, 76, 90, 128, 164, 30, 4, 0, 0, 1, 0, 0], "label": ""}, {"date": "20180314", "count": 762, "sum": 4094526, "histogram": [1, 4, 5, 9, 7, 11, 21, 34, 61, 87, 105, 159, 222, 30, 4, 2, 0, 0, 0, 0], "label": ""}, {"date": "20180313", "count": 740, "sum": 3938144, "histogram": [6, 3, 2, 11, 7, 16, 28, 24, 47, 79, 106, 150, 223, 37, 1, 0, 0, 0, 0, 0], "label": ""}, {"date": "20180312", "count": 494, "sum": 2748892, "histogram": [1, 5, 3, 0, 6, 16, 9, 14, 33, 36, 76, 110, 159, 25, 0, 1, 0, 0, 0, 0], "label": ""}], "kind": "exponential", "description": "Session restore: If a session is restored by the user clicking on 'Restore Session', this probe measures the time elapsed between the instant the user has clicked and the instant we have finished restoring tabs eagerly. At this stage, the tabs that are restored on demand are not restored yet."}