{"buckets": [0, 1, 2], "data": [{"date": "20180507", "count": 1, "sum": 35, "histogram": [0, 35, 0], "label": ""}, {"date": "20180506", "count": 13, "sum": 953, "histogram": [0, 953, 0], "label": ""}, {"date": "20180505", "count": 14, "sum": 995, "histogram": [310, 995, 0], "label": ""}, {"date": "20180504", "count": 20, "sum": 1088, "histogram": [0, 1088, 0], "label": ""}, {"date": "20180503", "count": 23, "sum": 1582, "histogram": [0, 1582, 0], "label": ""}, {"date": "20180502", "count": 13, "sum": 653, "histogram": [0, 653, 0], "label": ""}, {"date": "20180501", "count": 16, "sum": 375, "histogram": [415, 375, 0], "label": ""}, {"date": "20180430", "count": 17, "sum": 299, "histogram": [0, 299, 0], "label": ""}, {"date": "20180429", "count": 22, "sum": 577, "histogram": [605, 577, 0], "label": ""}, {"date": "20180428", "count": 18, "sum": 976, "histogram": [0, 976, 0], "label": ""}, {"date": "20180427", "count": 12, "sum": 1158, "histogram": [0, 1158, 0], "label": ""}, {"date": "20180426", "count": 13, "sum": 536, "histogram": [0, 536, 0], "label": ""}, {"date": "20180425", "count": 13, "sum": 164, "histogram": [0, 164, 0], "label": ""}, {"date": "20180424", "count": 18, "sum": 808, "histogram": [0, 808, 0], "label": ""}, {"date": "20180423", "count": 10, "sum": 387, "histogram": [617, 387, 0], "label": ""}, {"date": "20180422", "count": 9, "sum": 314, "histogram": [0, 314, 0], "label": ""}, {"date": "20180421", "count": 18, "sum": 1142, "histogram": [17, 1142, 0], "label": ""}, {"date": "20180420", "count": 18, "sum": 483, "histogram": [1206, 483, 0], "label": ""}, {"date": "20180419", "count": 24, "sum": 877, "histogram": [937, 877, 0], "label": ""}, {"date": "20180418", "count": 19, "sum": 462, "histogram": [388, 462, 0], "label": ""}, {"date": "20180417", "count": 10, "sum": 307, "histogram": [0, 307, 0], "label": ""}, {"date": "20180416", "count": 4, "sum": 41, "histogram": [0, 41, 0], "label": ""}, {"date": "20180415", "count": 28, "sum": 679, "histogram": [0, 679, 0], "label": ""}, {"date": "20180414", "count": 6, "sum": 188, "histogram": [0, 188, 0], "label": ""}, {"date": "20180413", "count": 11, "sum": 1063, "histogram": [0, 1063, 0], "label": ""}, {"date": "20180412", "count": 23, "sum": 951, "histogram": [68, 951, 0], "label": ""}, {"date": "20180411", "count": 11, "sum": 196, "histogram": [993, 196, 0], "label": ""}, {"date": "20180410", "count": 18, "sum": 406, "histogram": [744, 406, 0], "label": ""}, {"date": "20180409", "count": 223, "sum": 22581, "histogram": [0, 22581, 0], "label": ""}, {"date": "20180408", "count": 12, "sum": 1965, "histogram": [0, 1965, 0], "label": ""}, {"date": "20180407", "count": 11, "sum": 240, "histogram": [633, 240, 0], "label": ""}, {"date": "20180406", "count": 20, "sum": 596, "histogram": [1456, 596, 0], "label": ""}, {"date": "20180405", "count": 11, "sum": 674, "histogram": [0, 674, 0], "label": ""}, {"date": "20180404", "count": 10, "sum": 1319, "histogram": [0, 1319, 0], "label": ""}, {"date": "20180403", "count": 11, "sum": 361, "histogram": [135, 361, 0], "label": ""}, {"date": "20180402", "count": 13, "sum": 434, "histogram": [0, 434, 0], "label": ""}, {"date": "20180401", "count": 16, "sum": 798, "histogram": [174, 798, 0], "label": ""}, {"date": "20180331", "count": 33, "sum": 594, "histogram": [0, 594, 0], "label": ""}, {"date": "20180330", "count": 16, "sum": 1128, "histogram": [329, 1128, 0], "label": ""}, {"date": "20180329", "count": 16, "sum": 1345, "histogram": [0, 1345, 0], "label": ""}, {"date": "20180328", "count": 10, "sum": 471, "histogram": [0, 471, 0], "label": ""}, {"date": "20180327", "count": 7, "sum": 494, "histogram": [0, 494, 0], "label": ""}, {"date": "20180326", "count": 13, "sum": 560, "histogram": [0, 560, 0], "label": ""}, {"date": "20180325", "count": 16, "sum": 562, "histogram": [0, 562, 0], "label": ""}, {"date": "20180324", "count": 14, "sum": 613, "histogram": [0, 613, 0], "label": ""}, {"date": "20180323", "count": 7, "sum": 268, "histogram": [0, 268, 0], "label": ""}, {"date": "20180322", "count": 19, "sum": 610, "histogram": [1046, 610, 0], "label": ""}, {"date": "20180321", "count": 10, "sum": 244, "histogram": [0, 244, 0], "label": ""}, {"date": "20180320", "count": 16, "sum": 515, "histogram": [0, 515, 0], "label": ""}, {"date": "20180319", "count": 12, "sum": 335, "histogram": [542, 335, 0], "label": ""}, {"date": "20180318", "count": 27, "sum": 1603, "histogram": [0, 1603, 0], "label": ""}, {"date": "20180317", "count": 15, "sum": 683, "histogram": [834, 683, 0], "label": ""}, {"date": "20180316", "count": 13, "sum": 2200, "histogram": [0, 2200, 0], "label": ""}, {"date": "20180315", "count": 11, "sum": 526, "histogram": [82, 526, 0], "label": ""}, {"date": "20180314", "count": 21, "sum": 920, "histogram": [999, 920, 0], "label": ""}, {"date": "20180313", "count": 38, "sum": 5916, "histogram": [0, 5916, 0], "label": ""}, {"date": "20180312", "count": 51, "sum": 5766, "histogram": [0, 5766, 0], "label": ""}], "kind": "boolean", "description": "Whether a HTTP transaction routed via Alt-Svc was scheme=http"}